diffq/__init__.py
diffq/base.py
diffq/bitpack.cpython-38-darwin.so
diffq/diffq.py
diffq/lsq.py
diffq/torch_pack.py
diffq/ts_export.py
diffq/uniform.py
diffq/utils.py
diffq-0.2.4.dist-info/LICENSE
diffq-0.2.4.dist-info/METADATA
diffq-0.2.4.dist-info/WHEEL
diffq-0.2.4.dist-info/top_level.txt
diffq-0.2.4.dist-info/RECORD
